lobbyview/LobbyView.py
lobbyview/__init__.py
lobbyview/exceptions.py
lobbyview-0.0.6.dist-info/LICENSE
lobbyview-0.0.6.dist-info/METADATA
lobbyview-0.0.6.dist-info/WHEEL
lobbyview-0.0.6.dist-info/top_level.txt
lobbyview-0.0.6.dist-info/RECORD
