Metadata-Version: 2.1
Name: lobbyview
Version: 0.0.6
Summary: LobbyView Rest API Wrapper
Author-email: lobbyview <lobbydata@gmail.com>
Project-URL: LobbyViewRestAPI, https://rest-api.lobbyview.org/
Keywords: politics,lobbying
Requires-Python: >=3.5
License-File: LICENSE
Requires-Dist: python-dotenv==1.0.1
